yutto/__init__.py
yutto/__main__.py
yutto/__version__.py
yutto/api/__init__.py
yutto/api/bangumi.py
yutto/api/cheese.py
yutto/api/collection.py
yutto/api/danmaku.py
yutto/api/space.py
yutto/api/ugc_video.py
yutto/api/user_info.py
yutto/cli/__init__.py
yutto/cli/cli.py
yutto/cli/settings.py
yutto/download_manager.py
yutto/downloader/__init__.py
yutto/downloader/downloader.py
yutto/downloader/progressbar.py
yutto/downloader/selector.py
yutto/exceptions.py
yutto/extractor/__init__.py
yutto/extractor/_abc.py
yutto/extractor/bangumi.py
yutto/extractor/bangumi_batch.py
yutto/extractor/cheese.py
yutto/extractor/cheese_batch.py
yutto/extractor/collection.py
yutto/extractor/common.py
yutto/extractor/favourites.py
yutto/extractor/series.py
yutto/extractor/ugc_video.py
yutto/extractor/ugc_video_batch.py
yutto/extractor/user_all_favourites.py
yutto/extractor/user_all_ugc_videos.py
yutto/extractor/user_watch_later.py
yutto/input_parser.py
yutto/mcp_server.py
yutto/media/__init__.py
yutto/media/codec.py
yutto/media/quality.py
yutto/path_templates.py
yutto/py.typed
yutto/types.py
yutto/utils/__init__.py
yutto/utils/asynclib.py
yutto/utils/console/__init__.py
yutto/utils/console/attributes.py
yutto/utils/console/colorful.py
yutto/utils/console/formatter.py
yutto/utils/console/logger.py
yutto/utils/console/status_bar.py
yutto/utils/danmaku.py
yutto/utils/fetcher.py
yutto/utils/ffmpeg.py
yutto/utils/file_buffer.py
yutto/utils/filter.py
yutto/utils/functional/__init__.py
yutto/utils/functional/async_object.py
yutto/utils/functional/async_to_sync.py
yutto/utils/functional/data_access.py
yutto/utils/functional/filter_none_values.py
yutto/utils/functional/functional.py
yutto/utils/functional/singleton.py
yutto/utils/functional/xmerge.py
yutto/utils/metadata.py
yutto/utils/priority.py
yutto/utils/subtitle.py
yutto/utils/time.py
yutto/validator.py
yutto-2.1.0.dist-info/WHEEL
yutto-2.1.0.dist-info/entry_points.txt
yutto-2.1.0.dist-info/METADATA
yutto-2.1.0.dist-info/RECORD
