Metadata-Version: 2.3
Name: yutto
Version: 2.1.0
Summary: 🧊 一个可爱且任性的 B 站视频下载器
Keywords: python,bilibili,video,downloader,danmaku
Author: Nyakku Shigure
Author-email: Nyakku Shigure <sigure.qaq@gmail.com>
License: GPL-3.0
Classifier: Environment :: Console
Classifier: Operating System :: OS Independent
Classifier: License :: OSI Approved :: GNU General Public License v3 (GPLv3)
Classifier: Typing :: Typed
Classifier: Programming Language :: Python
Classifier: Programming Language :: Python :: 3
Classifier: Programming Language :: Python :: 3.10
Classifier: Programming Language :: Python :: 3.11
Classifier: Programming Language :: Python :: 3.12
Classifier: Programming Language :: Python :: 3.13
Classifier: Programming Language :: Python :: 3.14
Classifier: Programming Language :: Python :: Implementation :: CPython
Requires-Dist: aiofiles>=24.1.0
Requires-Dist: biliass==2.3.0
Requires-Dist: colorama>=0.4.6 ; sys_platform == 'win32'
Requires-Dist: typing-extensions>=4.15.0
Requires-Dist: dict2xml>=1.7.7
Requires-Dist: httpx[http2,socks]>=0.28.1
Requires-Dist: tomli>=2.2.1 ; python_full_version < '3.11'
Requires-Dist: pydantic>=2.12.0
Requires-Dist: returns>=0.26.0
Requires-Dist: fastmcp>=2.12.3 ; extra == 'mcp'
Requires-Python: >=3.10
Project-URL: Documentation, https://github.com/yutto-dev/yutto
Project-URL: Homepage, https://github.com/yutto-dev/yutto
Project-URL: Issues, https://github.com/yutto-dev/yutto/issues
Project-URL: Repository, https://github.com/yutto-dev/yutto
Provides-Extra: mcp
